qwen_llamaindex/__init__.py
qwen_llamaindex/base.py
qwen_llamaindex-1.0.2.dist-info/METADATA
qwen_llamaindex-1.0.2.dist-info/WHEEL
qwen_llamaindex-1.0.2.dist-info/top_level.txt
qwen_llamaindex-1.0.2.dist-info/RECORD
