Metadata-Version: 2.4
Name: qwen-llamaindex
Version: 1.0.2
Summary: Unofficial Qwen API Client For Llamaindex
Author-email: Ahmad Rosyihuddin <rosyihuddin.dev@gmail.com>
License: MIT
Project-URL: Homepage, https://github.com/arosyihuddin/qwen-api
Project-URL: Documentation, https://github.com/arosyihuddin/qwen-api
Project-URL: Repository, https://github.com/arosyihuddin/qwen-api
Project-URL: Issues, https://github.com/arosyihuddin/qwen-api/issues
Keywords: qwen,ai,llm,qwen-api
Classifier: Development Status :: 5 - Production/Stable
Classifier: Intended Audience :: Developers
Classifier: Topic :: Software Development :: Build Tools
Classifier: Programming Language :: Python :: 3
Classifier: Programming Language :: Python :: 3.11
Classifier: Programming Language :: Python :: 3.12
Classifier: Programming Language :: Python :: 3.13
Classifier: License :: OSI Approved :: MIT License
Classifier: Operating System :: OS Independent
Requires-Python: >=3.11
Requires-Dist: llama-index>=0.12.28
Requires-Dist: python-dotenv<2.0.0,>=1.1.0
Requires-Dist: qwen-api>=1.4.12
Provides-Extra: dev
Requires-Dist: pytest; extra == "dev"
Requires-Dist: black; extra == "dev"
Requires-Dist: mypy; extra == "dev"
